pipebar/__init__.py
pipebar/main.py
pipebar-1.0.1.dist-info/METADATA
pipebar-1.0.1.dist-info/WHEEL
pipebar-1.0.1.dist-info/top_level.txt
pipebar-1.0.1.dist-info/RECORD
