Metadata-Version: 2.4
Name: pipebar
Version: 1.0.1
Summary: Colorful terminal progress bar with ETA and speed tracking
Author-email: カネキ <fabfawufawd@gmail.com>
License-Expression: MIT
Keywords: progress,bar,terminal,CLI,ansi
Classifier: Programming Language :: Python :: 3
Classifier: Environment :: Console
Classifier: Operating System :: OS Independent
Classifier: Topic :: Utilities
Classifier: Development Status :: 5 - Production/Stable
Requires-Python: >=3.6
